MANIFEST.in
README.txt
setup.py
django_docviewer.egg-info/PKG-INFO
django_docviewer.egg-info/SOURCES.txt
django_docviewer.egg-info/dependency_links.txt
django_docviewer.egg-info/not-zip-safe
django_docviewer.egg-info/requires.txt
django_docviewer.egg-info/top_level.txt
docviewer/__init__.py
docviewer/admin.py
docviewer/forms.py
docviewer/helpers.py
docviewer/models.py
docviewer/pipeline.py
docviewer/search_indexes.py
docviewer/settings.py
docviewer/tasks.py
docviewer/urls.py
docviewer/views.py
docviewer/management/__init__.py
docviewer/management/commands/__init__.py
docviewer/management/commands/docviewer_createtasks.py
docviewer/management/commands/docviewer_revoke.py
docviewer/management/commands/generate_document.py
docviewer/migrations/0001_initial.py
docviewer/migrations/0002_auto__add_field_document_task_id__add_field_document_task_error.py
docviewer/migrations/0003_auto__add_field_document_task_start.py
docviewer/migrations/0004_auto__add_field_document_download__add_field_document_related_url.py
docviewer/migrations/0005_auto__add_field_document_filename.py
docviewer/migrations/__init__.py
docviewer/static/docviewer/css/print.css
docviewer/static/docviewer/css/components/annotations.css
docviewer/static/docviewer/css/components/minimode.css
docviewer/static/docviewer/css/components/pages.css
docviewer/static/docviewer/css/components/reset.css
docviewer/static/docviewer/css/components/structure.css
docviewer/static/docviewer/css/components/ui-footer.css
docviewer/static/docviewer/css/components/ui-header.css
docviewer/static/docviewer/css/components/ui-menu.css
docviewer/static/docviewer/css/components/ui-navigation.css
docviewer/static/docviewer/css/components/ui-search.css
docviewer/static/docviewer/css/components/ui-text.css
docviewer/static/docviewer/css/components/ui-zoom.css
docviewer/static/docviewer/css/components/ui.css
docviewer/static/docviewer/css/components/unsupported.css
docviewer/static/docviewer/css/components/view-annotations.css
docviewer/static/docviewer/css/components/view-document.css
docviewer/static/docviewer/css/components/view-search.css
docviewer/static/docviewer/css/components/view-text.css
docviewer/static/docviewer/css/components/view-thumbnails.css
