Metadata-Version: 1.0
Name: django-docviewer
Version: 0.4
Summary: documentcloud for django
Home-page: https://github.com/oxys-net/django-docviewer
Author: oxys
Author-email: contact@oxys.net
License: UNKNOWN
Platform: UNKNOWN
Classifier: Environment :: Web Environment
Classifier: Intended Audience :: Developers
Classifier: License :: OSI Approved :: Apache Software License
Classifier: Operating System :: OS Independent
Classifier: Programming Language :: Python
Classifier: Topic :: Utilities
